ruamel/yaml/jinja2/__init__.py
ruamel/yaml/jinja2/__plug_in__.py
ruamel.yaml.jinja2-0.2.7.dist-info/LICENSE
ruamel.yaml.jinja2-0.2.7.dist-info/METADATA
ruamel.yaml.jinja2-0.2.7.dist-info/WHEEL
ruamel.yaml.jinja2-0.2.7.dist-info/namespace_packages.txt
ruamel.yaml.jinja2-0.2.7.dist-info/top_level.txt
ruamel.yaml.jinja2-0.2.7.dist-info/RECORD
