Metadata-Version: 2.1
Name: ruamel.yaml.jinja2
Version: 0.2.7
Summary: jinja2 pre and post-processor to update with YAML
Home-page: https://sourceforge.net/p/ruamel-yaml-jinja2/code/ci/default/tree
Author: Anthon van der Neut
Author-email: a.van.der.neut@ruamel.eu
License: MIT
Keywords: yaml 1.2 parser round-trip jinja2
Platform: UNKNOWN
Classifier: Development Status :: 4 - Beta
Classifier: Intended Audience :: Developers
Classifier: License :: OSI Approved :: MIT License
Classifier: Operating System :: OS Independent
Classifier: Programming Language :: Python
Requires-Python: >=3.6
Requires-Dist: ruamel.yaml (>=0.16.1)
